wrong/__init__.py
wrong/sort/__init__.py
wrong/sort/sort.py
wrong-0.0.0.dist-info/METADATA
wrong-0.0.0.dist-info/RECORD
wrong-0.0.0.dist-info/WHEEL
wrong-0.0.0.dist-info/top_level.txt
