Metadata-Version: 2.1
Name: wrong
Version: 0.0.0
Summary: Evaluate your unit test skills
Home-page: https://github.com/seungjaeryanlee/wrong
Author: Seung Jae (Ryan) Lee
Author-email: seungjaeryanlee@gmail.com
License: UNKNOWN
Platform: UNKNOWN
Classifier: Programming Language :: Python :: 3
Classifier: License :: OSI Approved :: MIT License
Classifier: Operating System :: OS Independent
